dizbot/__init__.py
dizbot/dizbot.py
dizbot/dizbot_config.py
dizbot/dizbot_generator.py
dizbot/dizbot_utils.py
dizbot-1.0.3.dist-info/LICENSE
dizbot-1.0.3.dist-info/METADATA
dizbot-1.0.3.dist-info/WHEEL
dizbot-1.0.3.dist-info/entry_points.txt
dizbot-1.0.3.dist-info/top_level.txt
dizbot-1.0.3.dist-info/RECORD
