Metadata-Version: 2.1
Name: dizbot
Version: 1.0.3
Summary: A command line tool to seamlessly build discord bots in python
Home-page: https://github.com/eishan05/dizbot
Author: Eishan Lawrence
Author-email: eishanlawrence5@gmail.com
License: MIT
Keywords: dizbot,discord,discord.py,bot
Platform: UNKNOWN
Classifier: License :: OSI Approved :: MIT License
Classifier: Topic :: Utilities
Classifier: Programming Language :: Python :: 3.4
Classifier: Programming Language :: Python :: 3.5
Classifier: Programming Language :: Python :: 3.6
Classifier: Programming Language :: Python :: 3.7
Classifier: Programming Language :: Python :: 3.8
Requires-Python: >=3
Requires-Dist: click
Requires-Dist: discord.py
